atlantisbot_api/__init__.py
atlantisbot_api/admin.py
atlantisbot_api/api/__init__.py
atlantisbot_api/api/permissions.py
atlantisbot_api/api/serializers.py
atlantisbot_api/api/views.py
atlantisbot_api/apps.py
atlantisbot_api/management/commands/clear_secretsanta.py
atlantisbot_api/management/commands/roll_secretsanta.py
atlantisbot_api/migrations/0001_initial.py
atlantisbot_api/migrations/0002_auto_20201107_0011.py
atlantisbot_api/migrations/0003_auto_20201107_0018.py
atlantisbot_api/migrations/0004_auto_20201107_0019.py
atlantisbot_api/migrations/0005_auto_20201107_0133.py
atlantisbot_api/migrations/0006_auto_20201109_1903.py
atlantisbot_api/migrations/0007_discorduser_clan.py
atlantisbot_api/migrations/__init__.py
atlantisbot_api/models.py
atlantisbot_api/tests/__init__.py
atlantisbot_api/tests/test_amigo_secreto.py
atlantisbot_api/tests/test_discord_user.py
atlantisbot_api/tests/test_raids_state.py
atlantisbot_api/urls.py
atlantisbot_api-1.0.12.dist-info/LICENSE
atlantisbot_api-1.0.12.dist-info/METADATA
atlantisbot_api-1.0.12.dist-info/WHEEL
atlantisbot_api-1.0.12.dist-info/RECORD
