Metadata-Version: 2.1
Name: atlantisbot-api
Version: 1.0.12
Summary: Django App to interface with the AtlantisBot API
Home-page: https://github.com/johnvictorfs/atlantisbot-api
License: MIT
Author: John Victor
Author-email: johnvfs@protonmail.com
Requires-Python: >=3.7,<4.0
Classifier: License :: OSI Approved :: MIT License
Classifier: Programming Language :: Python :: 3
Classifier: Programming Language :: Python :: 3.7
Classifier: Programming Language :: Python :: 3.8
Classifier: Programming Language :: Python :: 3.9
Classifier: Programming Language :: Python :: 3.10
Classifier: Programming Language :: Python :: 3.11
Requires-Dist: django (>=2.2,<3.0)
Requires-Dist: djangorestframework (>=3.10.3,<4.0.0)
Requires-Dist: requests-oauthlib (>=1.3.0,<2.0.0)
Requires-Dist: requests[security] (>=2.23.0,<3.0.0)
Project-URL: Repository, https://github.com/johnvictorfs/atlantisbot-api
